sewar/__init__.py
sewar/command_line.py
sewar/full_ref.py
sewar/metrics.py
sewar/no_ref.py
sewar/utils.py
sewar-0.4.dist-info/METADATA
sewar-0.4.dist-info/RECORD
sewar-0.4.dist-info/WHEEL
sewar-0.4.dist-info/entry_points.txt
sewar-0.4.dist-info/top_level.txt
