Metadata-Version: 2.1
Name: sewar
Version: 0.4
Summary: All image quality metrics you need in one package.
Home-page: https://github.com/andrewekhalel/sewar
Author: Andrew Khalel
Author-email: andrewekhalel@gmail.com
License: MIT
Keywords: image quality performance metric measure ergas q psnr pansharpening
Platform: UNKNOWN
Classifier: Development Status :: 2 - Pre-Alpha
Classifier: License :: OSI Approved :: MIT License
Classifier: Operating System :: OS Independent
Classifier: Programming Language :: Python
Classifier: Programming Language :: Python :: 2
Classifier: Programming Language :: Python :: 2.6
Classifier: Programming Language :: Python :: 2.7
Classifier: Programming Language :: Python :: 3
Classifier: Programming Language :: Python :: 3.1
Classifier: Programming Language :: Python :: 3.2
Classifier: Programming Language :: Python :: 3.3
Classifier: Programming Language :: Python :: 3.4
Classifier: Programming Language :: Python :: 3.5
Classifier: Programming Language :: Python :: 3.6
Classifier: Topic :: Multimedia :: Graphics
Requires-Dist: numpy
Requires-Dist: scipy
Requires-Dist: Pillow
